ashishinstall/__init__.py
ashishinstall/ashishinstall.py
ashishinstall-0.0.1.dist-info/LICENSE
ashishinstall-0.0.1.dist-info/METADATA
ashishinstall-0.0.1.dist-info/WHEEL
ashishinstall-0.0.1.dist-info/top_level.txt
ashishinstall-0.0.1.dist-info/RECORD
