Metadata-Version: 2.1
Name: ashishinstall
Version: 0.0.1
Summary: A small example package
Home-page: https://github.com/ashish615/ashishinstall
Author: Ashish Patel
Author-email: ashish615@gmail.com
Classifier: Programming Language :: Python :: 3
Classifier: License :: OSI Approved :: MIT License
Classifier: Operating System :: OS Independent
License-File: LICENSE
Requires-Dist: pandas
